AutomaticDifferentiation/AutomaticDifferentiation.py
AutomaticDifferentiation/ReverseAD.py
AutomaticDifferentiation/__init__.py
AutomaticDifferentiation-0.0.2.dist-info/LICENSE
AutomaticDifferentiation-0.0.2.dist-info/METADATA
AutomaticDifferentiation-0.0.2.dist-info/WHEEL
AutomaticDifferentiation-0.0.2.dist-info/top_level.txt
AutomaticDifferentiation-0.0.2.dist-info/RECORD
