Metadata-Version: 2.1
Name: AutomaticDifferentiation
Version: 0.0.2
Summary: Fall2021 CS107 Automatic Diff Project
Home-page: https://github.com/cs107-sandbox/cs107-FinalProject
Author: Gahyun Sung
Author-email: gsung@g.harvard.edu
License: UNKNOWN
Platform: UNKNOWN
Classifier: Intended Audience :: Developers
Classifier: Programming Language :: Python :: 3
Classifier: Topic :: Software Development :: Libraries :: Python Modules
Requires-Python: >=3.6
License-File: LICENSE
